pyretailscience/__init__.py
pyretailscience/constants.py
pyretailscience/options.py
pyretailscience/plugin.py
pyretailscience/analysis/__init__.py
pyretailscience/analysis/cohort.py
pyretailscience/analysis/composite_rank.py
pyretailscience/analysis/cross_shop.py
pyretailscience/analysis/customer.py
pyretailscience/analysis/customer_decision_hierarchy.py
pyretailscience/analysis/gain_loss.py
pyretailscience/analysis/haversine.py
pyretailscience/analysis/product_association.py
pyretailscience/analysis/revenue_tree.py
pyretailscience/assets/fonts/Poppins-Bold.ttf
pyretailscience/assets/fonts/Poppins-LightItalic.ttf
pyretailscience/assets/fonts/Poppins-Medium.ttf
pyretailscience/assets/fonts/Poppins-Regular.ttf
pyretailscience/assets/fonts/Poppins-SemiBold.ttf
pyretailscience/plots/__init__.py
pyretailscience/plots/area.py
pyretailscience/plots/bar.py
pyretailscience/plots/broken_timeline.py
pyretailscience/plots/cohort.py
pyretailscience/plots/heatmap.py
pyretailscience/plots/histogram.py
pyretailscience/plots/index.py
pyretailscience/plots/line.py
pyretailscience/plots/period_on_period.py
pyretailscience/plots/price.py
pyretailscience/plots/scatter.py
pyretailscience/plots/time.py
pyretailscience/plots/tree_diagram.py
pyretailscience/plots/venn.py
pyretailscience/plots/waterfall.py
pyretailscience/plots/styles/__init__.py
pyretailscience/plots/styles/colors.py
pyretailscience/plots/styles/font_utils.py
pyretailscience/plots/styles/graph_utils.py
pyretailscience/plots/styles/styling_helpers.py
pyretailscience/segmentation/__init__.py
pyretailscience/segmentation/hml.py
pyretailscience/segmentation/rfm.py
pyretailscience/segmentation/segstats.py
pyretailscience/segmentation/threshold.py
pyretailscience/utils/__init__.py
pyretailscience/utils/date.py
pyretailscience/utils/filter_and_label.py
pyretailscience/utils/label.py
pyretailscience-0.42.0.dist-info/METADATA
pyretailscience-0.42.0.dist-info/WHEEL
pyretailscience-0.42.0.dist-info/licenses/LICENSE
pyretailscience-0.42.0.dist-info/RECORD
