Metadata-Version: 2.4
Name: pyretailscience
Version: 0.42.0
Summary: Retail Data Science Tools
Author-email: Murray Vanwyk <2493311+mvanwyk@users.noreply.github.com>
License-Expression: Elastic-2.0
License-File: LICENSE
Classifier: License :: Other/Proprietary License
Classifier: Operating System :: OS Independent
Classifier: Programming Language :: Python :: 3
Classifier: Programming Language :: Python :: 3.10
Classifier: Programming Language :: Python :: 3.11
Classifier: Programming Language :: Python :: 3.12
Classifier: Programming Language :: Python :: 3.13
Requires-Python: <3.14,>=3.10
Requires-Dist: duckdb<2,>=1.0.0
Requires-Dist: ibis-framework[duckdb]<11,>=10.0.0
Requires-Dist: matplotlib-set-diagrams~=0.0.2
Requires-Dist: matplotlib<4,>=3.9.1
Requires-Dist: numpy<=2,>=1.26.3
Requires-Dist: pandas<3,>=2.2.3
Requires-Dist: pyarrow<23,>=18.0.0
Requires-Dist: scikit-learn<2,>=1.4.2
Requires-Dist: scipy<2,>=1.14.1
Requires-Dist: textalloc>=1.2.1
Requires-Dist: toml<0.11,>=0.10.2
Requires-Dist: tqdm<5,>=4.66.1
